{
"best_photos": [
{"f": "catalog/image/adulam1.jpg", "t": "Blossom in Adulam park", "loc": "Adulam park", "tags": "adulam winter 2020 02"},
{"f": "catalog/image/anavim1.jpg", "t": "Grapes of Gush Etzion winery", "loc": "Gush Etzion", "tags": "grapes gushetzion autumn 2015 09"},
{"f": "catalog/image/anavim2.jpg", "t": "Grapes of Gush Etzion winery", "loc": "Gush Etzion", "tags": "grapes gushetzion summer 2019 08"},
{"f": "catalog/image/anavim3.jpg", "t": "Grapes of Gush Etzion winery", "loc": "Gush Etzion", "tags": "grapes gushetzion summer 2019 08"},
{"f": "catalog/image/anavim6.jpg", "t": "Grapes in Gush Etzion", "loc": "Gush Etzion", "tags": "grapes gushetzion autumn 2019 11"},
{"f": "catalog/image/arugot1.jpg", "t": "Arugot stream", "loc": "Arugot stream", "tags": "arugot autumn 2018 10"},
{"f": "catalog/image/arugot2.jpg", "t": "Arugot stream", "loc": "Arugot stream", "tags": "arugot summer 2020 07"},
{"f": "catalog/image/arugot3.jpg", "t": "Arugot stream", "loc": "Arugot stream", "tags": "arugot summer 2020 07"},
{"f": "catalog/image/arugot4.jpg", "t": "View on Arugot stream", "loc": "Arugot stream", "tags": "arugot winter 2021 02"},
{"f": "catalog/image/arugot5.jpg", "t": "View on Arugot stream", "loc": "Arugot stream", "tags": "arugot autumn 2016 10"},
{"f": "catalog/image/arugot6.jpg", "t": "Arugot stream", "loc": "Arugot stream", "tags": "arugot autumn 2016 10"},
{"f": "catalog/image/arugot7.jpg", "t": "View on Arugot stream", "loc": "Arugot stream", "tags": "arugot"},
{"f": "catalog/image/autumn1.jpg", "t": "Pomegranate", "loc": "Gush Etzion", "tags": "gushetzion autumn 2017 10"},
{"f": "catalog/image/autumn2.jpg", "t": "Nahal Hapirim", "loc": "Gush Etzion", "tags": "pomegranate autumn 2017 11"},
{"f": "catalog/image/autumn3.jpg", "t": "Pomegranate", "loc": "Gush Etzion", "tags": "autumn 2015 10"},
{"f": "catalog/image/autumn4.jpg", "t": "Lonely leaf", "loc": "Gush Etzion", "tags": "leaf autumn 2015 10"},
{"f": "catalog/image/autumn5.jpg", "t": "Pardes of Pomegranate", "loc": "Gush Etzion", "tags": "pomegranate autumn 2017 10"},
{"f": "catalog/image/autumn6.jpg", "t": "Nahal Hapirim", "loc": "Gush Etzion", "tags": "grapes autumn 2020 11"},
{"f": "catalog/image/autumn7.jpg", "t": "Neve Daniel", "loc": "Gush Etzion", "tags": "autumn autumn 2016 11"},
{"f": "catalog/image/autumn8.jpg", "t": "Nahal Hapirim", "loc": "Gush Etzion", "tags": "autumn autumn 2016 11"},
{"f": "catalog/image/autumn9.jpg", "t": "Neve Daniel", "loc": "Gush Etzion", "tags": "autumn autumn 2016 11"},
{"f": "catalog/image/autumn10.jpg", "t": "Vineyards", "loc": "Gush Etzion", "tags": "autumn"},
{"f": "catalog/image/banias1.jpg", "t": "Banias Waterfall", "loc": "Banias stream", "tags": "banias summer 2020 08"},
{"f": "catalog/image/banias2.jpg", "t": "Banias", "loc": "Banias stream", "tags": "banias winter 2024 12"},
{"f": "catalog/image/baram1.jpg", "t": "Kfar Bar'am Synagogue", "loc": "Bar'am National Park", "tags": "baram spring 2016 05"},
{"f": "catalog/image/batayin1.jpg", "t": "Bat Ayin", "loc": "Gush Etzion", "tags": "batayin gushetzion winter 2020 02"},
{"f": "catalog/image/batayin2.jpg", "t": "Bat Ayin", "loc": "Gush Etzion", "tags": "batayin gushetzion winter 2019 02"},
{"f": "catalog/image/batayin3.jpg", "t": "Bat Ayin", "loc": "Gush Etzion", "tags": "batayin gushetzion winter 2020 12"},
{"f": "catalog/image/beitgovrin1.jpg", "t": "Beit Govrin", "loc": "Beit Govrin National Park", "tags": "beitgovrin spring 2016 03"},
{"f": "catalog/image/beitgovrin2.jpg", "t": "Beit Govrin", "loc": "Beit Govrin National Park", "tags": "beitgovrin spring 2016 03"},
{"f": "catalog/image/beitshean1.jpg", "t": "Ancient ruins of Beit She'an ", "loc": "Beit Shean National Park", "tags": "beitshean summer 2016 08"},
{"f": "catalog/image/beitshean2.jpg", "t": "Ancient ruins of Beit She'an", "loc": "Beit Shean National Park", "tags": "beitshean"},
{"f": "catalog/image/beitzait1.jpg", "t": "Beit Zayit Reservoir", "loc": "Beit Zayit", "tags": "beitzait spring 2019 04"},
{"f": "catalog/image/bloom1.jpg", "t": "Pomegranate", "loc": "Gush Etzion", "tags": "bloom gushetzion autumn 2017 09"},
{"f": "catalog/image/bloom2.jpg", "t": "Reflection", "loc": "Gush Etzion", "tags": "bloom gushetzion winter 2017 12"},
{"f": "catalog/image/bloom3.jpg", "t": "Darom Adom", "loc": "Southern Israel", "tags": "bloom daromadom winter 2020 02"},
{"f": "catalog/image/bloom4.jpg", "t": "Crocus hyemalis", "loc": "Gush Etzion", "tags": "bloom gushetzion winter 2016 12"},
{"f": "catalog/image/bloom5.jpg", "t": "Herodion view", "loc": "Gush Etzion", "tags": "bloom gushetzion winter 2017 02"},
{"f": "catalog/image/bloom6.jpg", "t": "Crocus hyemalis", "loc": "Gush Etzion", "tags": "bloom winter 2019 12"},
{"f": "catalog/image/bloom7.jpg", "t": "Almond blossom", "loc": "Gush Etzion", "tags": "bloom winter 2018 02"},
{"f": "catalog/image/bloom8.jpg", "t": "Amat Habiar", "loc": "Gush Etzion", "tags": "bloom spring 2018 03"},
{"f": "catalog/image/bloom9.jpg", "t": "Nahal Tkoa", "loc": "Gush Etzion", "tags": "bloom winter 2018 12"},
{"f": "catalog/image/bloom10.jpg", "t": "Blossom", "loc": "Gush Etzion", "tags": "bloom winter 2021 02"},
{"f": "catalog/image/bloom11.jpg", "t": "Colchicum", "loc": "Gush Etzion", "tags": "bloom autumn 2018 11"},
{"f": "catalog/image/bloom12.jpg", "t": "Cyclamens", "loc": "Jerusalem forest", "tags": "bloom spring 2017 03"},
{"f": "catalog/image/bloom13.jpg", "t": "Blossom in Adulam park", "loc": "Adulam park", "tags": "bloom winter 2019 02"},
{"f": "catalog/image/bloom14.jpg", "t": "Anemones", "loc": "Darom Adom", "tags": "bloom daromadom winter 2020 02"},
{"f": "catalog/image/bloom15.jpg", "t": "Anemone", "loc": "Darom Adom", "tags": "bloom daromadom winter 2020 02"},
{"f": "catalog/image/bloom16.jpg", "t": "Cyclamens", "loc": "Adulam park", "tags": "bloom winter 2020 02"},
{"f": "catalog/image/bloom17.jpg", "t": "Anemones", "loc": "Adulam park", "tags": "bloom winter 2021 02"},
{"f": "catalog/image/bloom18.jpg", "t": "Anemones and Cyclamens", "loc": "Jerusalem", "tags": "bloom winter 2021 02"},
{"f": "catalog/image/bloom19.jpg", "t": "Almond tree", "loc": "Jerusalem", "tags": "bloom winter 2020 02"},
{"f": "catalog/image/bloom20.jpg", "t": "Almond tree", "loc": "Gush Etzion", "tags": "bloom gushetzion winter 2021 02"},
{"f": "catalog/image/bloom21.jpg", "t": "Crocus hyemalis", "loc": "Gush Etzion", "tags": "bloom gushetzion autumn 2020 11"},
{"f": "catalog/image/bloom22.jpg", "t": "Almond tree in snow", "loc": "Gush Etzion", "tags": "bloom winter 2021 02"},
{"f": "catalog/image/bloom23.jpg", "t": "Crocus hyemalis", "loc": "Gush Etzion", "tags": "bloom autumn 2020 11"},
{"f": "catalog/image/bloom24.jpg", "t": "Colchicum", "loc": "Gush Etzion", "tags": "bloom autumn 2020 11"},
{"f": "catalog/image/bloom25.jpg", "t": "Crocus hyemalis after rain", "loc": "Jerusalem", "tags": "bloom autumn 2023 11"},
{"f": "catalog/image/bloom26.jpg", "t": "Butterfly on Colchicum", "loc": "Gush Etzion", "tags": "bloom autumn 2020 11"},
{"f": "catalog/image/bloom27.jpg", "t": "Blossom in Gush Etzion after rain", "loc": "Gush Etzion", "tags": "bloom gushetzion spring 2023 03"},
{"f": "catalog/image/bloom28.jpg", "t": "Anemones", "loc": "Gush Etzion", "tags": "bloom spring 2023 03"},
{"f": "catalog/image/bloom29.jpg", "t": "Cyclamens with dew", "loc": "Adulam park", "tags": "bloom winter 2021 02"},
{"f": "catalog/image/bloom30.jpg", "t": "Moraea sisyrinchium", "loc": "Gush Etzion", "tags": "bloom spring 2021 03"},
{"f": "catalog/image/bloom31.jpg", "t": "Anemones", "loc": "Adulam park", "tags": "bloom winter 2021 02"},
{"f": "catalog/image/bloom32.jpg", "t": "Anemones in Shokeda forest", "loc": "Darom Adom", "tags": "bloom winter 2018 02"},
{"f": "catalog/image/bloom33.jpg", "t": "Blossom", "loc": "Jerusalem forest", "tags": "bloom spring 2017 04"},
{"f": "catalog/image/bloom34.jpg", "t": "Blossom", "loc": "", "tags": "bloom spring 2017 03"},
{"f": "catalog/image/bloom35.jpg", "t": "Almond blossom", "loc": "Darom Adom", "tags": "bloom winter 2017 02"},
{"f": "catalog/image/bloom36.jpg", "t": "Blossom", "loc": "Darom Adom", "tags": "bloom winter 2017 02"},
{"f": "catalog/image/bloom37.jpg", "t": "Almond blossom", "loc": "", "tags": "bloom winter 2016 02"},
{"f": "catalog/image/bloom38.jpg", "t": "Almond blossom", "loc": "", "tags": "bloom winter 2016 02"},
{"f": "catalog/image/bluecave2.jpg", "t": "The Blue cave", "loc": "Dor HaBonim Beach Nature Reserve", "tags": "bluecave dor sea autumn 2020 09"},
{"f": "catalog/image/brihatdubek1.jpg", "t": "Dubek's Pool", "loc": "Gush Etzion", "tags": "brihatdubek gushetzion winter 2020 02"},
{"f": "catalog/image/cesaria1.jpg", "t": "Sunset in Cesaria", "loc": "Cesaria", "tags": "cesaria sea spring 2022 04"},
{"f": "catalog/image/deadsea1.jpg", "t": "Dead sea pools", "loc": "Dead sea", "tags": "deadsea spring 2017 03"},
{"f": "catalog/image/deadsea2.jpg", "t": "Dead sea view", "loc": "Dead sea", "tags": "deadsea summer 2016 06"},
{"f": "catalog/image/deadsea3.jpg", "t": "Dead sea pools", "loc": "Dead sea", "tags": "deadsea winter 2017 02"},
{"f": "catalog/image/deadsea4.jpg", "t": "Dead sea salt formations", "loc": "Dead sea", "tags": "deadsea winter 2017 02"},
{"f": "catalog/image/deadsea5.jpg", "t": "Dead sea view", "loc": "Dead sea", "tags": "deadsea summer 2022 08"},
{"f": "catalog/image/derehavot11.jpg", "t": "Dereh Avot", "loc": "Gush Etzion", "tags": "derehavot spring 2020 03"},
{"f": "catalog/image/derehavot13.jpg", "t": "Dereh Avot", "loc": "Gush Etzion", "tags": "derehavot autumn 2019 11"},
{"f": "catalog/image/derehavot15.jpg", "t": "Dereh Avot", "loc": "Gush Etzion", "tags": "derehavot summer 2019 06"},
{"f": "catalog/image/derehavot16.jpg", "t": "Dereh Avot", "loc": "Gush Etzion", "tags": "derehavot autumn 2021 11"},
{"f": "catalog/image/derehavot3.jpg", "t": "Dereh Avot", "loc": "Gush Etzion", "tags": "derehavot winter 2019 02"},
{"f": "catalog/image/derehavot5.jpg", "t": "Dereh Avot", "loc": "Gush Etzion", "tags": "derehavot"},
{"f": "catalog/image/efrat1.jpg", "t": "Efrat", "loc": "Gush Etzion", "tags": "efrat winter 2019 01"},
{"f": "catalog/image/efrat2.jpg", "t": "Efrat", "loc": "Gush Etzion", "tags": "efrat spring 2018 04"},
{"f": "catalog/image/efrat3.jpg", "t": "Efrat", "loc": "Gush Etzion", "tags": "efrat summer 2020 07"},
{"f": "catalog/image/efrat4.jpg", "t": "Efrat", "loc": "Gush Etzion", "tags": "efrat autumn 2018 11"},
{"f": "catalog/image/einabukleb1.jpg", "t": "Ein Abu Caleb", "loc": "Gush Etzion", "tags": "einabukleb spring 2017 04"},
{"f": "catalog/image/einabukleb2.jpg", "t": "Ein Abu Caleb", "loc": "Gush Etzion", "tags": "einabukleb autumn 2020 11"},
{"f": "catalog/image/einelkasis2.jpg", "t": "Ein El-kasis", "loc": "Gush Etzion", "tags": "einelkasis spring 2019 03"},
{"f": "catalog/image/einelkasis5.jpg", "t": "Ein El-kasis", "loc": "Gush Etzion", "tags": "einelkasis spring 2019 04"},
{"f": "catalog/image/einitzhak4.jpg", "t": "Ein Itzhak", "loc": "Gush Etzion", "tags": "einitzhak summer 2020 07"},
{"f": "catalog/image/einitzhak7.jpg", "t": "Ein Itzhak", "loc": "Gush Etzion", "tags": "einitzhak spring 2020 05"},
{"f": "catalog/image/einkshatot1.jpg", "t": "Maayan Hakshatot", "loc": "Mavo Horon", "tags": "einkshatot winter 2023 02"},
{"f": "catalog/image/einlivne4.jpg", "t": "Ein Livne", "loc": "Gush Etzion", "tags": "einlivne autumn 2020 10"},
{"f": "catalog/image/einlivne5.jpg", "t": "Ein Livne", "loc": "Gush Etzion", "tags": "einlivne summer 2019 07"},
{"f": "catalog/image/einmaim1.jpg", "t": "Ein Maim", "loc": "Gush Etzion", "tags": "einmaim summer 2020 06"},
{"f": "catalog/image/einmigdal.jpg", "t": "Ein Migdal", "loc": "Emek HaMaayanot Regional Council", "tags": "einmigdal spring 2025 03"},
{"f": "catalog/image/einprat1.jpg", "t": "Ein Prat", "loc": "Wadi Qelt", "tags": "einprat winter 2019 12"},
{"f": "catalog/image/einprat2.jpg", "t": "Ein Prat", "loc": "Wadi Qelt", "tags": "einprat winter 2019 12"},
{"f": "catalog/image/einyorkeam.jpg", "t": "Ein Yorkeam", "loc": "Big Crater of Yeruham", "tags": "einyorkeam winter 2023 01"},
{"f": "catalog/image/foresteretzayalim1.jpg", "t": "Eretz Ayalim forest", "loc": "Gush Etzion", "tags": "forest eretzayalim winter 2020 02"},
{"f": "catalog/image/foresteretzayalim4.jpg", "t": "Eretz Ayalim forest", "loc": "Gush Etzion", "tags": "forest eretzayalim winter 2019 12"},
{"f": "catalog/image/gesherkantra1.jpg", "t": "Kantra bridge", "loc": "Emek HaMaayanot Regional Council", "tags": "gesher kantra summer 2020 07"},
{"f": "catalog/image/golan1.jpg", "t": "Orvim waterfall", "loc": "Golan Heights", "tags": "golan winter 2024 02"},
{"f": "catalog/image/golan2.jpg", "t": "El Al stream, Black waterfall", "loc": "Golan Heights", "tags": "golan autumn 2023 09"},
{"f": "catalog/image/golan3.jpg", "t": "Ein Tut", "loc": "Golan Heights", "tags": "golan autumn 2023 10"},
{"f": "catalog/image/golan4.jpg", "t": "Sunset over Kineret", "loc": "Golan Heights", "tags": "golan autumn 2023 10"},
{"f": "catalog/image/golan5.jpg", "t": "Zavitan stream", "loc": "Golan Heights", "tags": "golan winter 2024 01"},
{"f": "catalog/image/golan6.jpg", "t": "Irusim waterfall", "loc": "Golan Heights", "tags": "golan winter 2024 01"},
{"f": "catalog/image/golan7.jpg", "t": "Wadi Nov", "loc": "Golan Heights", "tags": "golan winter 2024 02"},
{"f": "catalog/image/golan8.jpg", "t": "Southern Golan promenade", "loc": "Golan Heights", "tags": "golan spring 2024 03"},
{"f": "catalog/image/golan9.jpg", "t": "Yehudiya pools", "loc": "Golan Heights", "tags": "golan spring 2024 04"},
{"f": "catalog/image/golan10.jpg", "t": "Keshet pool", "loc": "Golan Heights", "tags": "golan spring 2024 05"},
{"f": "catalog/image/golan11.jpg", "t": "Seasonal flows", "loc": "Golan Heights", "tags": "golan summer 2024 06"},
{"f": "catalog/image/golan12.jpg", "t": "Ein Pik", "loc": "Golan Heights", "tags": "golan autumn 2023 10"},
{"f": "catalog/image/golan13.jpg", "t": "Einot Eden", "loc": "Golan Heights", "tags": "golan autumn 2023 09"},
{"f": "catalog/image/golan14.jpg", "t": "Drimia", "loc": "Golan Heights", "tags": "golan autumn 2023 09"},
{"f": "catalog/image/golan15.jpg", "t": "Sunrise in Nov Meadow", "loc": "Golan Heights", "tags": "golan winter 2024 01"},
{"f": "catalog/image/golan16.jpg", "t": "Zavitan stream", "loc": "Golan Heights", "tags": "golan winter 2024 01"},
{"f": "catalog/image/golan17.jpg", "t": "Morning fog in Moshav Nov", "loc": "Golan Heights", "tags": "golan spring 2024 05"},
{"f": "catalog/image/golan18.jpg", "t": "Morning fog in Nov Meadow", "loc": "Golan Heights", "tags": "golan spring 2024 05"},
{"f": "catalog/image/golan19.jpg", "t": "Sunset over Kineret", "loc": "Golan Heights", "tags": "golan autumn 2023 11"},
{"f": "catalog/image/golan20.jpg", "t": "Irus of Golan", "loc": "Golan Heights", "tags": "golan spring 2024 03"},
{"f": "catalog/image/golan21.jpg", "t": "Gamla peak", "loc": "Golan Heights", "tags": "golan spring 2024 03"},
{"f": "catalog/image/golan22.jpg", "t": "Iris mesopotamica", "loc": "Golan Heights", "tags": "golan spring 2024 04"},
{"f": "catalog/image/golan23.jpg", "t": "View on reservoir and Hermon", "loc": "Golan Heights", "tags": "golan spring 2024 04"},
{"f": "catalog/image/golan24.jpg", "t": "Yehudiya stream", "loc": "Golan Heights", "tags": "golan winter 2024 01"},
{"f": "catalog/image/golan25.jpg", "t": "Gilabun waterfall", "loc": "Golan Heights", "tags": "golan spring 2024 04"},
{"f": "catalog/image/golan26.jpg", "t": "Wadi Nov", "loc": "Golan Heights", "tags": "golan winter 2024 01"},
{"f": "catalog/image/golan27.jpg", "t": "Meitzar nature reserve", "loc": "Golan Heights", "tags": "golan spring 2024 03"},
{"f": "catalog/image/golan28.jpg", "t": "Wadi Nov", "loc": "Golan Heights", "tags": "golan winter 2024 02"},
{"f": "catalog/image/golan29.jpg", "t": "Sunrise in Nov Meadow", "loc": "Golan Heights", "tags": "golan winter 2024 01"},
{"f": "catalog/image/golan30.jpg", "t": "Wadi Nov", "loc": "Golan Heights", "tags": "golan winter 2024 02"},
{"f": "catalog/image/golan31.jpg", "t": "Wadi Nov", "loc": "Golan Heights", "tags": "golan"},
{"f": "catalog/image/golan32.jpg", "t": "Horses in Golan", "loc": "Golan Heights", "tags": "golan winter 2024 02"},
{"f": "catalog/image/golan33.jpg", "t": "Ein Nov", "loc": "Golan Heights", "tags": "golan summer 2024 06"},
{"f": "catalog/image/golan35.jpg", "t": "Growing Hadass(myrtle) in Nov", "loc": "Golan Heights", "tags": "golan autumn 2024 09"},
{"f": "catalog/image/golan38.jpg", "t": "Blue lupines in Nov", "loc": "Golan Heights", "tags": "golan spring 2024 03"},
{"f": "catalog/image/golan39.jpg", "t": "View on Kineret", "loc": "Golan Heights", "tags": "golan winter 2024 01"},
{"f": "catalog/image/golan40.jpg", "t": "View on Kineret", "loc": "Golan Heights", "tags": "golan winter 2024 01"},
{"f": "catalog/image/golan41.jpg", "t": "Wadi Nov", "loc": "Golan Heights", "tags": "golan winter 2024 01"},
{"f": "catalog/image/golan42.jpg", "t": "Bajuria", "loc": "Golan Heights", "tags": "golan winter 2024 01"},
{"f": "catalog/image/golan43.jpg", "t": "Ein Tut", "loc": "Golan Heights", "tags": "golan winter 2024 01"},
{"f": "catalog/image/golan44.jpg", "t": "Katzrin waterfall", "loc": "Golan Heights", "tags": "golan winter 2024 02"},
{"f": "catalog/image/golan45.jpg", "t": "View on Hermon", "loc": "Golan Heights", "tags": "golan winter 2024 02"},
{"f": "catalog/image/golan46.jpg", "t": "Katzr Bardawil", "loc": "Golan Heights", "tags": "golan winter 2024 02"},
{"f": "catalog/image/golan47.jpg", "t": "Reservoir overflow", "loc": "Golan Heights", "tags": "golan winter 2024 02"},
{"f": "catalog/image/golan48.jpg", "t": "Seasonal flows", "loc": "Golan Heights", "tags": "golan winter 2024 02"},
{"f": "catalog/image/golan49.jpg", "t": "Seasonal flows", "loc": "Golan Heights", "tags": "golan winter 2024 02"},
{"f": "catalog/image/golan50.jpg", "t": "Seasonal flows", "loc": "Golan Heights", "tags": "golan winter 2024 02"},
{"f": "catalog/image/golan51.jpg", "t": "Seasonal flows", "loc": "Golan Heights", "tags": "golan winter 2024 02"},
{"f": "catalog/image/golan52.jpg", "t": "Fishgop viewpoint, Afik", "loc": "Golan Heights", "tags": "golan winter 2024 02"},
{"f": "catalog/image/golan53.jpg", "t": "El Al nature reserve", "loc": "Golan Heights", "tags": "golan winter 2024 02"},
{"f": "catalog/image/golan54.jpg", "t": "El Al nature reserve", "loc": "Golan Heights", "tags": "golan winter 2024 02"},
{"f": "catalog/image/golan55.jpg", "t": "View on Hermon", "loc": "Golan Heights", "tags": "golan spring 2024 03"},
{"f": "catalog/image/golan56.jpg", "t": "View on Kineret", "loc": "Golan Heights", "tags": "golan spring 2024 03"},
{"f": "catalog/image/golan57.jpg", "t": "View on Kineret", "loc": "Golan Heights", "tags": "golan spring 2024 03"},
{"f": "catalog/image/golan58.jpg", "t": "Yarmuk River", "loc": "Golan Heights", "tags": "golan spring 2024 03"},
{"f": "catalog/image/golan59.jpg", "t": "Hamat Gader road", "loc": "Golan Heights", "tags": "golan spring 2024 03"},
{"f": "catalog/image/golan62.jpg", "t": "View on Hermon", "loc": "Golan Heights", "tags": "golan spring 2025 04"},
{"f": "catalog/image/golan63.jpg", "t": "Gilabun waterfall", "loc": "Golan Heights", "tags": "golan winter 2025 01"},
{"f": "catalog/image/golan64.jpg", "t": "Ein Kshatot Ancient Synagogue", "loc": "Golan Heights", "tags": "golan winter 2024 12"},
{"f": "catalog/image/golan65.jpg", "t": "Ein Ayub waterfall", "loc": "Kineret", "tags": "golan winter 2024 12"},
{"f": "catalog/image/golan66.jpg", "t": "View on Hermon", "loc": "Golan Heights", "tags": "golan spring 2025 04"},
{"f": "catalog/image/golan67.jpg", "t": "Sunset", "loc": "Kineret", "tags": "golan spring 2025 04"},
{"f": "catalog/image/golan68.jpg", "t": "Gamla", "loc": "Golan Heights", "tags": "golan spring 2024 03"},
{"f": "catalog/image/golan69.jpg", "t": "El Al nature reserve", "loc": "Golan Heights", "tags": "golan autumn 2024 09"},
{"f": "catalog/image/golan70.jpg", "t": "View on Kineret", "loc": "Golan Heights", "tags": "golan autumn 2024 10"},
{"f": "catalog/image/golan71.jpg", "t": "Cows in Golan", "loc": "Golan Heights", "tags": "golan spring 2025 05"},
{"f": "catalog/image/golan73.jpg", "t": "Sternbergia in Tel Hazeka", "loc": "Golan Heights", "tags": "golan autumn 2024 10"},
{"f": "catalog/image/havatsfarhamidbar2.jpg", "t": "Havat Sfar Hamidbar", "loc": "Gush Etzion", "tags": "havatsfarhamidbar winter 2019 02"},
{"f": "catalog/image/helmoniyot1.jpg", "t": "Sternbergia", "loc": "Gush Etzion", "tags": "helmoniyot autumn 2018 11"},
{"f": "catalog/image/helmoniyot2.jpg", "t": "Sternbergia", "loc": "Gush Etzion", "tags": "helmoniyot autumn 2018 11"},
{"f": "catalog/image/helmoniyot3.jpg", "t": "Sternbergia", "loc": "Gush Etzion", "tags": "helmoniyot autumn 2020 11"},
{"f": "catalog/image/helmoniyot5.jpg", "t": "Sternbergia", "loc": "Gush Etzion", "tags": "helmoniyot autumn 2018 11"},
{"f": "catalog/image/herodion1.jpg", "t": "Herodion", "loc": "Gush Etzion", "tags": "herodion winter 2019 02"},
{"f": "catalog/image/herodion2.jpg", "t": "Herodion", "loc": "Gush Etzion", "tags": "herodion winter 2021 12"},
{"f": "catalog/image/jerusalem1.jpg", "t": "Ancient buildings", "loc": "Jerusalem", "tags": "jerusalem"},
{"f": "catalog/image/maayanharod1.jpg", "t": "Maayan Harod national park", "loc": "Maayan Harod", "tags": "maayanharod summer 2020 08"},
{"f": "catalog/image/marsaba1.jpg", "t": "Mar Saba monastery", "loc": "Mar Saba", "tags": "marsaba"},
{"f": "catalog/image/metzada1.jpg", "t": "Masada", "loc": "Masada", "tags": "metzada winter 2021 12"},
{"f": "catalog/image/metzada2.jpg", "t": "Masada", "loc": "Masada", "tags": "metzada winter 2021 12"},
{"f": "catalog/image/mitzporzvika1.jpg", "t": "Zvika viewpoint", "loc": "Gush Etzion", "tags": "mitzporzvika summer 2020 06"},
{"f": "catalog/image/nahalhapirim1.jpg", "t": "Nahal Hapirim", "loc": "Gush Etzion", "tags": "nahalhapirim"},
{"f": "catalog/image/nahalhapirim2.jpg", "t": "Nahal Hapirim", "loc": "Gush Etzion", "tags": "nahalhapirim spring 2022 03"},
{"f": "catalog/image/nahalhapirim7.jpg", "t": "Nahal Hapirim", "loc": "Gush Etzion", "tags": "nahalhapirim summer 2021 06"},
{"f": "catalog/image/nahalhapirim8.jpg", "t": "Nahal Hapirim", "loc": "Gush Etzion", "tags": "nahalhapirim spring 2018 04"},
{"f": "catalog/image/nahalhapirim11.jpg", "t": "Nahal Hapirim", "loc": "Gush Etzion", "tags": "nahalhapirim winter 2017 12"},
{"f": "catalog/image/nahalhapirim21.jpg", "t": "Nahal Hapirim", "loc": "Gush Etzion", "tags": "nahalhapirim winter 2019 12"},
{"f": "catalog/image/nahalhapirim22.jpg", "t": "Nahal Hapirim", "loc": "Gush Etzion", "tags": "nahalhapirim winter 2022 12"},
{"f": "catalog/image/nahalkziv1.jpg", "t": "Nahal Kziv", "loc": "Upper Galilee", "tags": "nahalkziv summer 2020 08"},
{"f": "catalog/image/nahalkziv2.jpg", "t": "Nahal Kziv", "loc": "Upper Galilee", "tags": "nahalkziv summer 2020 08"},
{"f": "catalog/image/nahalkziv3.jpg", "t": "Nahal Kziv", "loc": "Upper Galilee", "tags": "nahalkziv summer 2020 08"},
{"f": "catalog/image/nahalkziv4.jpg", "t": "Nahal Kziv", "loc": "Upper Galilee", "tags": "nahalkziv spring 2022 04"},
{"f": "catalog/image/nahalkziv5.jpg", "t": "Nahal Kziv", "loc": "Upper Galilee", "tags": "nahalkziv spring 2022 04"},
{"f": "catalog/image/nahaltkoa1.jpg", "t": "Nahal Tkoa", "loc": "Gush Etzion", "tags": "nahaltkoa winter 2017 02"},
{"f": "catalog/image/nahaltkoa8.jpg", "t": "Nahal Tkoa", "loc": "Gush Etzion", "tags": "nahaltkoa spring 2020 03"},
{"f": "catalog/image/nevedaniel5.jpg", "t": "Neve Daniel", "loc": "Gush Etzion", "tags": "nevedaniel winter 2015 01"},
{"f": "catalog/image/nevedaniel6.jpg", "t": "Neve Daniel", "loc": "Gush Etzion", "tags": "nevedaniel spring 2017 04"},
{"f": "catalog/image/ofanaim1.jpg", "t": "Gush Etzion single track", "loc": "Gush Etzion", "tags": "ofanaim autumn 2019 09"},
{"f": "catalog/image/parpar1.jpg", "t": "Butterfly", "loc": "Gush Etzion", "tags": "parpar spring 2019 04"},
{"f": "catalog/image/rain1.jpg", "t": "Rain in the forest", "loc": "Gush Etzion", "tags": "rain spring 2023 03"},
{"f": "catalog/image/sahne1.jpg", "t": "Sakhne", "loc": "Gan HaShlosha National Park", "tags": "sakhne summer 2019 08"},
{"f": "catalog/image/sahne2.jpg", "t": "Sakhne", "loc": "Gan HaShlosha National Park", "tags": "sakhne summer 2019 08"},
{"f": "catalog/image/sdeboaz1.jpg", "t": "Sde Boaz", "loc": "Gush Etzion", "tags": "sdeboaz spring 2020 05"},
{"f": "catalog/image/sdeboaz2.jpg", "t": "Sde Boaz", "loc": "Gush Etzion", "tags": "sdeboaz spring 2020 05"},
{"f": "catalog/image/sea1.jpg", "t": "Sunset at the sea", "loc": "Israeli coastal plain", "tags": "sea summer 2016 07"},
{"f": "catalog/image/sunset1.jpg", "t": "Sunset over Kfar Etzion", "loc": "Gush Etzion", "tags": "sunset summer 2021 06"},
{"f": "catalog/image/tazpithabanim1.jpg", "t": "The Boys Promenade", "loc": "Gush Etzion", "tags": "tazpithabanim spring 2016 05"},
{"f": "catalog/image/tazpithabanim2.jpg", "t": "The Boys Promenade", "loc": "Gush Etzion", "tags": "tazpithabanim summer 2020 07"},
{"f": "catalog/image/telazeka1.jpg", "t": "Tel Azeka hill", "loc": "Tel Azeka", "tags": "telazeka spring 2016 03"},
{"f": "catalog/image/yaartkoa1.jpg", "t": "Tkoa forest", "loc": "Gush Etzion", "tags": "yaartkoa winter 2020 02"},
{"f": "catalog/image/yaartkoa2.jpg", "t": "Tkoa forest", "loc": "Gush Etzion", "tags": "yaartkoa winter 2020 02"},

{"f": "golan/images/map/big/ahunov3.jpg", "t": "Blossom in Nov Meadow Nature Reserve", "loc": "Golan Heights", "tags": "nov meadow bloom golan winter 2025 01"},
{"f": "golan/images/map/big/ahunov4.jpg", "t": "Blossom in Nov Meadow Nature Reserve", "loc": "Golan Heights", "tags": "nov meadow bloom golan winter 2025 01"},
{"f": "golan/images/map/big/ahunov5.jpg", "t": "Blossom in Nov Meadow Nature Reserve", "loc": "Golan Heights", "tags": "nov meadow bloom golan winter 2025 01"},
{"f": "golan/images/map/big/ahunov6.jpg", "t": "Blossom in Nov Meadow Nature Reserve", "loc": "Golan Heights", "tags": "nov meadow bloom golan winter 2025 01"},
{"f": "golan/images/map/big/ahunov8.jpg", "t": "Blossom in Nov Meadow Nature Reserve", "loc": "Golan Heights", "tags": "nov meadow bloom golan winter 2025 01"},
{"f": "golan/images/map/big/ahunov9.jpg", "t": "Blossom in Nov Meadow Nature Reserve", "loc": "Golan Heights", "tags": "nov meadow bloom golan winter 2025 02"},
{"f": "golan/images/map/big/ahunov11.jpg", "t": "Blossom in Nov Meadow Nature Reserve", "loc": "Golan Heights", "tags": "nov meadow bloom golan winter 2025 02"},
{"f": "golan/images/map/big/ahunov12.jpg", "t": "Blossom in Nov Meadow Nature Reserve", "loc": "Golan Heights", "tags": "nov meadow bloom golan winter 2025 02"},
{"f": "golan/images/map/big/ahunov13.jpg", "t": "Blossom in Nov Meadow Nature Reserve", "loc": "Golan Heights", "tags": "nov meadow bloom golan winter 2025 02"},
{"f": "golan/images/map/big/bajoriya2.jpg", "t": "Bajuria", "loc": "Golan Heights", "tags": "bajuriya spring 2024 05"},
{"f": "golan/images/map/big/einkef1.jpg", "t": "Ein Kef", "loc": "Golan Heights", "tags": "einkef autumn 2023 09"},
{"f": "golan/images/map/big/einkshatot2.jpg", "t": "Ein Kshatot view", "loc": "Golan Heights", "tags": "einkshatot winter 2024 12"},
{"f": "golan/images/map/big/einkshatot4.jpg", "t": "Ein Kshatot Ancient Synagogue", "loc": "Golan Heights", "tags": "einkshatot winter 2024 12"},
{"f": "golan/images/map/big/einkshatot5.jpg", "t": "Ein Kshatot", "loc": "Golan Heights", "tags": "einkshatot winter 2024 12"},
{"f": "golan/images/map/big/einkshatot6.jpg", "t": "Ein Kshatot Ancient Synagogue", "loc": "Golan Heights", "tags": "einkshatot winter 2024 12"},
{"f": "golan/images/map/big/einkshatot7.jpg", "t": "Ein Kshatot Ancient Synagogue", "loc": "Golan Heights", "tags": "einkshatot winter 2024 12"},
{"f": "golan/images/map/big/einkshatot8.jpg", "t": "Ein Kshatot view", "loc": "Golan Heights", "tags": "einkshatot winter 2024 12"},
{"f": "golan/images/map/big/einkshatot9.jpg", "t": "Ein Kshatot hall", "loc": "Golan Heights", "tags": "einkshatot winter 2024 12"},
{"f": "golan/images/map/big/einoteden2.jpg", "t": "Einot Eden", "loc": "Golan Heights", "tags": "einoteden autumn 2023 09"},
{"f": "golan/images/map/big/einoteden3.jpg", "t": "Einot Eden", "loc": "Golan Heights", "tags": "einoteden autumn 2023 09"},
{"f": "golan/images/map/big/einpik2.jpg", "t": "Ein Pik", "loc": "Golan Heights", "tags": "einpik autumn 2023 10"},
{"f": "golan/images/map/big/eintaufik1.jpg", "t": "Ein Taufik", "loc": "Golan Heights", "tags": "eintaufik autumn 2023 11"},
{"f": "golan/images/map/big/eintaufik2.jpg", "t": "Ein Taufik", "loc": "Golan Heights", "tags": "eintaufik autumn 2023 11"},
{"f": "golan/images/map/big/eintaufik3.jpg", "t": "Ein Taufik", "loc": "Golan Heights", "tags": "eintaufik autumn 2023 11"},
{"f": "golan/images/map/big/eintut2.jpg", "t": "Ein Tut", "loc": "Golan Heights", "tags": "eintut winter 2024 01"},
{"f": "golan/images/map/big/elal2.jpg", "t": "El Al stream, White waterfall", "loc": "Golan Heights", "tags": "elal autumn 2023 09"},
{"f": "golan/images/map/big/elal3.jpg", "t": "El Al nature reserve", "loc": "Golan Heights", "tags": "elal winter 2024 12"},
{"f": "golan/images/map/big/elal4.jpg", "t": "El Al nature reserve", "loc": "Golan Heights", "tags": "elal autumn 2023 09"},
{"f": "golan/images/map/big/elal5.jpg", "t": "El Al nature reserve", "loc": "Golan Heights", "tags": "elal autumn 2023 11"},
{"f": "golan/images/map/big/elal6.jpg", "t": "El Al stream, White waterfall", "loc": "Golan Heights", "tags": "elal autumn 2023 09"},
{"f": "golan/images/map/big/gamla1.jpg", "t": "Gamla", "loc": "Golan Heights", "tags": "gamla spring 2024 03"},
{"f": "golan/images/map/big/gamla2.jpg", "t": "Gamla waterfall", "loc": "Golan Heights", "tags": "gamla spring 2024 03"},
{"f": "golan/images/map/big/gamla3.jpg", "t": "Gamla peak", "loc": "Golan Heights", "tags": "gamla spring 2024 03"},
{"f": "golan/images/map/big/gamla4.jpg", "t": "Gamla", "loc": "Golan Heights", "tags": "gamla autumn 2023 10"},
{"f": "golan/images/map/big/juhader1.jpg", "t": "Juhader", "loc": "Golan Heights", "tags": "juhader summer 2024 06"},
{"f": "golan/images/map/big/juhader2.jpg", "t": "Juhader", "loc": "Golan Heights", "tags": "juhader autumn 2023 11"},
{"f": "golan/images/map/big/maayankanaf1.jpg", "t": "Maayan Kanaf", "loc": "Golan Heights", "tags": "maayankanaf autumn 2024 11"},
{"f": "golan/images/map/big/maayankanaf2.jpg", "t": "Maayan Kanaf", "loc": "Golan Heights", "tags": "maayankanaf summer 2024 08"},
{"f": "golan/images/map/big/maayankanaf3.jpg", "t": "Maayan Kanaf", "loc": "Golan Heights", "tags": "maayankanaf spring 2024 04"},
{"f": "golan/images/map/big/mapalirusim2.jpg", "t": "Irusim waterfall", "loc": "Golan Heights", "tags": "mapalirusim winter 2024 01"},
{"f": "golan/images/map/big/mapalirusim3.jpg", "t": "Irusim waterfall", "loc": "Golan Heights", "tags": "mapalirusim winter 2024 01"},
{"f": "golan/images/map/big/mapalirusim4.jpg", "t": "Irusim waterfall", "loc": "Golan Heights", "tags": "mapalirusim winter 2024 01"},
{"f": "golan/images/map/big/mapalirusim7.jpg", "t": "Irusim waterfall", "loc": "Golan Heights", "tags": "mapalirusim spring 2024 03"},
{"f": "golan/images/map/big/mapalirusim9.jpg", "t": "Irus of Golan", "loc": "Golan Heights", "tags": "mapalirusim spring 2024 03"},
{"f": "golan/images/map/big/mapalirusim10.jpg", "t": "Irus of Golan", "loc": "Golan Heights", "tags": "mapalirusim spring 2024 03"},
{"f": "golan/images/map/big/meitzar2.jpg", "t": "Meitzar nature reserve", "loc": "Golan Heights", "tags": "meitzar spring 2024 03"},
{"f": "golan/images/map/big/mitzpedima1.jpg", "t": "Dima viewpoint, Gshur", "loc": "Golan Heights", "tags": "mitzpedima spring 2024 05"},
{"f": "golan/images/map/big/mitzpedima2.jpg", "t": "Dima viewpoint, Gshur", "loc": "Golan Heights", "tags": "mitzpedima spring 2024 05"},
{"f": "golan/images/map/big/mitzpedima3.jpg", "t": "Dima viewpoint, Gshur", "loc": "Golan Heights", "tags": "mitzpedima spring 2024 05"},
{"f": "golan/images/map/big/mitzpedima4.jpg", "t": "Dima viewpoint, Gshur", "loc": "Golan Heights", "tags": "mitzpedima spring 2024 05"},
{"f": "golan/images/map/big/mitzpefishgop2.jpg", "t": "Fishgop viewpoint, Afik", "loc": "Golan Heights", "tags": "mitzpefishgop summer 2024 08"},
{"f": "golan/images/map/big/mitzpefishgop3.jpg", "t": "Fishgop viewpoint, Afik", "loc": "Golan Heights", "tags": "mitzpefishgop summer 2024 08"},
{"f": "golan/images/map/big/mitzpefishgop4.jpg", "t": "Fishgop viewpoint, Afik", "loc": "Golan Heights", "tags": "mitzpefishgop summer 2024 08"},
{"f": "golan/images/map/big/mitzpefishgop5.jpg", "t": "Fishgop viewpoint, Afik", "loc": "Golan Heights", "tags": "mitzpefishgop winter 2024 01"},
{"f": "golan/images/map/big/mitzpefishgop6.jpg", "t": "Fishgop viewpoint, Afik", "loc": "Golan Heights", "tags": "mitzpefishgop winter 2024 12"},
{"f": "golan/images/map/big/mitzpefishgop7.jpg", "t": "Fishgop viewpoint, Afik", "loc": "Golan Heights", "tags": "mitzpefishgop winter 2024 12"},
{"f": "golan/images/map/big/nov2.jpg", "t": "Moshav Nov", "loc": "Golan Heights", "tags": "nov winter 2023 12"},
{"f": "golan/images/map/big/nov5.jpg", "t": "Moshav Nov", "loc": "Golan Heights", "tags": "nov spring 2024 03"},
{"f": "golan/images/map/big/nov6.jpg", "t": "Moshav Nov", "loc": "Golan Heights", "tags": "nov autumn 2024 09"},
{"f": "golan/images/map/big/nov7.jpg", "t": "Moshav Nov", "loc": "Golan Heights", "tags": "nov summer 2024 07"},
{"f": "golan/images/map/big/nov9.jpg", "t": "Moshav Nov", "loc": "Golan Heights", "tags": "nov winter 2023 12"},
{"f": "golan/images/map/big/samach1.jpg", "t": "Nahal Samach", "loc": "Golan Heights", "tags": "samach spring 2024 04"},
{"f": "golan/images/map/big/samach2.jpg", "t": "Nahal Samach", "loc": "Golan Heights", "tags": "samach spring 2024 04"},
{"f": "golan/images/map/big/samach3.jpg", "t": "Nahal Samach", "loc": "Golan Heights", "tags": "samach spring 2024 04"},
{"f": "golan/images/map/big/samach4.jpg", "t": "Nahal Samach", "loc": "Golan Heights", "tags": "samach spring 2024 04"},
{"f": "golan/images/map/big/samach5.jpg", "t": "Nahal Samach", "loc": "Golan Heights", "tags": "samach spring 2024 04"},
{"f": "golan/images/map/big/samach6.jpg", "t": "Nahal Samach", "loc": "Golan Heights", "tags": "samach spring 2024 04"},
{"f": "golan/images/map/big/samach7.jpg", "t": "Nahal Samach", "loc": "Golan Heights", "tags": "samach spring 2024 04"},
{"f": "golan/images/map/big/samach8.jpg", "t": "Nahal Samach", "loc": "Golan Heights", "tags": "samach spring 2024 04"},
{"f": "golan/images/map/big/samach9.jpg", "t": "Nahal Samach", "loc": "Golan Heights", "tags": "samach spring 2024 04"},
{"f": "golan/images/map/big/tayeletdromhagolan2.jpg", "t": "Southern Golan promenade", "loc": "Golan Heights", "tags": "tayeletdromhagolan spring 2024 03"},
{"f": "golan/images/map/big/tayeletdromhagolan3.jpg", "t": "Southern Golan promenade", "loc": "Golan Heights", "tags": "tayeletdromhagolan spring 2024 03"},
{"f": "golan/images/map/big/tayeletdromhagolan4.jpg", "t": "Southern Golan promenade", "loc": "Golan Heights", "tags": "tayeletdromhagolan spring 2024 03"},
{"f": "golan/images/map/big/tayeletdromhagolan5.jpg", "t": "Southern Golan promenade", "loc": "Golan Heights", "tags": "tayeletdromhagolan spring 2024 03"},
{"f": "golan/images/map/big/tayeletdromhagolan6.jpg", "t": "Southern Golan promenade", "loc": "Golan Heights", "tags": "tayeletdromhagolan spring 2024 03"},
{"f": "golan/images/map/big/tayeletdromhagolan7.jpg", "t": "Southern Golan promenade", "loc": "Golan Heights", "tags": "tayeletdromhagolan spring 2024 03"},
{"f": "golan/images/map/big/tayeletmavohama3.jpg", "t": "Mavo Hama promenade", "loc": "Golan Heights", "tags": "tayeletmavohama winter 2024 01"},
{"f": "golan/images/map/big/tayeletmavohama4.jpg", "t": "Mavo Hama promenade", "loc": "Golan Heights", "tags": "tayeletmavohama winter 2024 02"},
{"f": "golan/images/map/big/tayeletmavohama5.jpg", "t": "Mavo Hama promenade", "loc": "Golan Heights", "tags": "tayeletmavohama winter 2024 02"},
{"f": "golan/images/map/big/tayeletmavohama6.jpg", "t": "Mavo Hama promenade", "loc": "Golan Heights", "tags": "tayeletmavohama spring 2024 03"},
{"f": "golan/images/map/big/tayeletmavohama7.jpg", "t": "Mavo Hama promenade", "loc": "Golan Heights", "tags": "tayeletmavohama spring 2024 03"},
{"f": "golan/images/map/big/yaarmavohama1.jpg", "t": "Mavo Hama forest", "loc": "Golan Heights", "tags": "yaarmavohama autumn 2023 11"},
{"f": "golan/images/map/big/yaarmavohama2.jpg", "t": "Mavo Hama forest", "loc": "Golan Heights", "tags": "yaarmavohama autumn 2023 11"},
{"f": "golan/images/map/big/yaarmavohama3.jpg", "t": "Mavo Hama forest", "loc": "Golan Heights", "tags": "yaarmavohama autumn 2023 11"},

{"f": "chrome_extension/golanphotos/elal46.jpg", "t": "El Al nature reserve", "loc": "Golan Heights", "tags": "elal autumn 2025 10"},
{"f": "chrome_extension/golanphotos/elal47.jpg", "t": "El Al nature reserve", "loc": "Golan Heights", "tags": "elal autumn 2025 10"},
{"f": "chrome_extension/golanphotos/elal49.jpg", "t": "El Al nature reserve", "loc": "Golan Heights", "tags": "elal autumn 2025 10"},
{"f": "chrome_extension/golanphotos/elal5.jpg", "t": "El Al nature reserve", "loc": "Golan Heights", "tags": "elal autumn 2023 09"},
{"f": "chrome_extension/golanphotos/elal50.jpg", "t": "El Al nature reserve", "loc": "Golan Heights", "tags": "elal autumn 2025 10"},
{"f": "chrome_extension/golanphotos/elal51.jpg", "t": "El Al nature reserve", "loc": "Golan Heights", "tags": "elal autumn 2025 10"},
{"f": "chrome_extension/golanphotos/elal52.jpg", "t": "El Al nature reserve", "loc": "Golan Heights", "tags": "elal autumn 2025 10"},
{"f": "chrome_extension/golanphotos/elal55.jpg", "t": "El Al stream, Black waterfall", "loc": "Golan Heights", "tags": "elal autumn 2025 10"},
{"f": "chrome_extension/golanphotos/elal56.jpg", "t": "El Al nature reserve", "loc": "Golan Heights", "tags": "elal autumn 2025 10"},
{"f": "chrome_extension/golanphotos/elal57.jpg", "t": "El Al nature reserve", "loc": "Golan Heights", "tags": "elal autumn 2025 10"},
{"f": "chrome_extension/golanphotos/hatzavim6.jpg", "t": "Flowering of marigolds", "loc": "Golan Heights", "tags": "hatzavim autumn 2025 09"},
{"f": "chrome_extension/golanphotos/hatzavim7.jpg", "t": "Flowering of marigolds", "loc": "Golan Heights", "tags": "hatzavim autumn 2025 09"},
{"f": "chrome_extension/golanphotos/hatzavim8.jpg", "t": "Flowering of marigolds", "loc": "Golan Heights", "tags": "hatzavim autumn 2025 09"},
{"f": "chrome_extension/golanphotos/hatzavim9.jpg", "t": "Flowering of marigolds", "loc": "Golan Heights", "tags": "hatzavim autumn 2025 09"},
{"f": "chrome_extension/golanphotos/hatzavim10.jpg", "t": "Flowering of marigolds", "loc": "Golan Heights", "tags": "hatzavim autumn 2025 10"},
{"f": "chrome_extension/golanphotos/mifgashhanahalim17.jpg", "t": "Mifgash Hanahalim", "loc": "Golan Heights", "tags": "mifgashhanahalim spring 2025 05"},
{"f": "chrome_extension/golanphotos/mifgashhanahalim18.jpg", "t": "Mifgash Hanahalim", "loc": "Golan Heights", "tags": "mifgashhanahalim spring 2025 05"},
{"f": "chrome_extension/golanphotos/mifgashhanahalim19.jpg", "t": "Mifgash Hanahalim", "loc": "Golan Heights", "tags": "mifgashhanahalim autumn 2025 10"},
{"f": "chrome_extension/golanphotos/mifgashhanahalim20.jpg", "t": "Mifgash Hanahalim", "loc": "Golan Heights", "tags": "mifgashhanahalim autumn 2025 10"},
{"f": "chrome_extension/golanphotos/mifgashhanahalim21.jpg", "t": "Mifgash Hanahalim", "loc": "Golan Heights", "tags": "mifgashhanahalim autumn 2025 10"},
{"f": "chrome_extension/golanphotos/mifgashhanahalim22.jpg", "t": "Mifgash Hanahalim", "loc": "Golan Heights", "tags": "mifgashhanahalim autumn 2025 10"},
{"f": "chrome_extension/golanphotos/nov15.jpg", "t": "Stork's nest in Moshav Nov", "loc": "Golan Heights", "tags": "nov summer 2024 07"},
{"f": "chrome_extension/golanphotos/nov16.jpg", "t": "Frozen Hadass in Moshav Nov", "loc": "Golan Heights", "tags": "nov winter 2025 02"},
{"f": "chrome_extension/golanphotos/nov17.jpg", "t": "Frozen Hadass in Moshav Nov", "loc": "Golan Heights", "tags": "nov winter 2025 02"},
{"f": "chrome_extension/golanphotos/nov18.jpg", "t": "Frozen Hadass in Moshav Nov", "loc": "Golan Heights", "tags": "nov winter 2025 02"},
{"f": "chrome_extension/golanphotos/nov19.jpg", "t": "Frozen Hadass in Moshav Nov", "loc": "Golan Heights", "tags": "nov winter 2025 02"},
{"f": "chrome_extension/golanphotos/nov20.jpg", "t": "Frozen Hadass in Moshav Nov", "loc": "Golan Heights", "tags": "nov winter 2025 02"},
{"f": "chrome_extension/golanphotos/nov21.jpg", "t": "Frozen Hadass in Moshav Nov", "loc": "Golan Heights", "tags": "nov winter 2025 02"},
{"f": "chrome_extension/golanphotos/nov23.jpg", "t": "Sunset in Moshav Nov", "loc": "Golan Heights", "tags": "nov spring 2025 05"},
{"f": "chrome_extension/golanphotos/nov24.jpg", "t": "A cowshed in Moshav Nov", "loc": "Golan Heights", "tags": "nov spring 2025 05"},
{"f": "chrome_extension/golanphotos/nov25.jpg", "t": "Moshav Nov", "loc": "Golan Heights", "tags": "nov spring 2025 05"},
{"f": "chrome_extension/golanphotos/nov26.jpg", "t": "Moshav Nov", "loc": "Golan Heights", "tags": "nov spring 2025 05"},
{"f": "chrome_extension/golanphotos/nov27.jpg", "t": "Stork's nest in Moshav Nov", "loc": "Golan Heights", "tags": "nov spring 2025 05"},
{"f": "chrome_extension/golanphotos/nov28.jpg", "t": "Moshav Nov", "loc": "Golan Heights", "tags": "nov summer 2025 07"},
{"f": "chrome_extension/golanphotos/nov29.jpg", "t": "Moshav Nov", "loc": "Golan Heights", "tags": "nov summer 2025 07"},
{"f": "chrome_extension/golanphotos/nov30.jpg", "t": "Sunset in Moshav Nov", "loc": "Golan Heights", "tags": "nov summer 2025 08"},
{"f": "chrome_extension/golanphotos/nov31.jpg", "t": "Moshav Nov", "loc": "Golan Heights", "tags": "nov autumn 2025 09"},
{"f": "chrome_extension/golanphotos/zavitan20.jpg", "t": "Zavitan, Yehudiya Nature reserve", "loc": "Golan Heights", "tags": "zavitan autumn 2025 10"},
{"f": "chrome_extension/golanphotos/zavitan21.jpg", "t": "Zavitan stream", "loc": "Golan Heights", "tags": "zavitan autumn 2025 10"},
{"f": "chrome_extension/golanphotos/zavitan22.jpg", "t": "Zavitan stream", "loc": "Golan Heights", "tags": "zavitan autumn 2025 10"},
{"f": "chrome_extension/golanphotos/zavitan23.jpg", "t": "Zavitan stream", "loc": "Golan Heights", "tags": "zavitan autumn 2025 10"},
{"f": "chrome_extension/golanphotos/zavitan24.jpg", "t": "Zavitan stream", "loc": "Golan Heights", "tags": "zavitan autumn 2025 10"},
{"f": "chrome_extension/golanphotos/zavitan25.jpg", "t": "Zavitan stream", "loc": "Golan Heights", "tags": "zavitan autumn 2025 10"},
{"f": "chrome_extension/golanphotos/zavitan26.jpg", "t": "Zavitan stream", "loc": "Golan Heights", "tags": "zavitan autumn 2025 10"},
{"f": "chrome_extension/golanphotos/zavitan27.jpg", "t": "Zavitan stream", "loc": "Golan Heights", "tags": "zavitan autumn 2025 10"},

{"f": "gush-etzion-album/image/amatmaim1.jpg", "t": "Amat Hamaim", "loc": "Gush Etzion", "tags": "amatmaim winter 2020 12"},
{"f": "gush-etzion-album/image/bloom2.jpg", "t": "Dereh Avot", "loc": "Gush Etzion", "tags": "bloom spring 2020 03"},
{"f": "gush-etzion-album/image/bloom12.jpg", "t": "Nahal Tkoa", "loc": "Gush Etzion", "tags": "bloom winter 2020 02"},
{"f": "gush-etzion-album/image/brihatdubek1.jpg", "t": "Dubek's Pool", "loc": "Gush Etzion", "tags": "brihatdubek winter 2020 02"},
{"f": "gush-etzion-album/image/brihatdubek2.jpg", "t": "Dubek's Pool", "loc": "Gush Etzion", "tags": "brihatdubek summer 2021 06"},
{"f": "gush-etzion-album/image/brihatdubek5.jpg", "t": "Dubek's Pool", "loc": "Gush Etzion", "tags": "brihatdubek winter 2020 02"},
{"f": "gush-etzion-album/image/brihatdubek6.jpg", "t": "Dubek's Pool", "loc": "Gush Etzion", "tags": "brihatdubek winter 2020 02"},
{"f": "gush-etzion-album/image/derehavot1.jpg", "t": "Dereh Avot", "loc": "Gush Etzion", "tags": "derehavot"},
{"f": "gush-etzion-album/image/derehavot6.jpg", "t": "Dereh Avot", "loc": "Gush Etzion", "tags": "derehavot winter 2019 02"},
{"f": "gush-etzion-album/image/derehavot7.jpg", "t": "Dereh Avot", "loc": "Gush Etzion", "tags": "derehavot spring 2017 03"},
{"f": "gush-etzion-album/image/derehavot8.jpg", "t": "Dereh Avot", "loc": "Gush Etzion", "tags": "derehavot spring 2018 03"},
{"f": "gush-etzion-album/image/derehavot9.jpg", "t": "Dereh Avot", "loc": "Gush Etzion", "tags": "derehavot spring 2021 04"},
{"f": "gush-etzion-album/image/derehavot10.jpg", "t": "Dereh Avot", "loc": "Gush Etzion", "tags": "derehavot spring 2020 04"},
{"f": "gush-etzion-album/image/derehavot14.jpg", "t": "Dereh Avot", "loc": "Gush Etzion", "tags": "derehavot autumn 2019 11"},
{"f": "gush-etzion-album/image/derehavot16.jpg", "t": "Dereh Avot", "loc": "Gush Etzion", "tags": "derehavot winter 2020 12"},
{"f": "gush-etzion-album/image/derehavot17.jpg", "t": "Dereh Avot", "loc": "Gush Etzion", "tags": "derehavot autumn 2020 09"},
{"f": "gush-etzion-album/image/derehavot18.jpg", "t": "Old Mikve on Dereh Avot", "loc": "Gush Etzion", "tags": "derehavot autumn 2012 09"},
{"f": "gush-etzion-album/image/derehavot19.jpg", "t": "Old Mikve on Dereh Avot", "loc": "Gush Etzion", "tags": "derehavot winter 2021 01"},
{"f": "gush-etzion-album/image/einabukleb2.jpg", "t": "Ein Abu Caleb", "loc": "Gush Etzion", "tags": "einabukleb summer 2021 06"},
{"f": "gush-etzion-album/image/einabukleb3.jpg", "t": "Ein Abu Caleb", "loc": "Gush Etzion", "tags": "einabukleb summer 2021 06"},
{"f": "gush-etzion-album/image/einabukleb4.jpg", "t": "Ein Abu Caleb", "loc": "Gush Etzion", "tags": "einabukleb summer 2021 06"},
{"f": "gush-etzion-album/image/einabukleb5.jpg", "t": "Ein Abu Caleb", "loc": "Gush Etzion", "tags": "einabukleb summer 2021 06"},
{"f": "gush-etzion-album/image/einelkasis1.jpg", "t": "Ein El-kasis", "loc": "Gush Etzion", "tags": "einelkasis spring 2019 04"},
{"f": "gush-etzion-album/image/einelkasis3.jpg", "t": "Ein El-kasis", "loc": "Gush Etzion", "tags": "einelkasis spring 2019 04"},
{"f": "gush-etzion-album/image/einelkasis4.jpg", "t": "Ein El-kasis", "loc": "Gush Etzion", "tags": "einelkasis spring 2019 03"},
{"f": "gush-etzion-album/image/einelmeara1.jpg", "t": "Ein El-Meara", "loc": "Gush Etzion", "tags": "einelmeara spring 2020 03"},
{"f": "gush-etzion-album/image/einelmeara4.jpg", "t": "Ein El-Meara", "loc": "Gush Etzion", "tags": "einelmeara winter 2021 01"},
{"f": "gush-etzion-album/image/einhubela1.jpg", "t": "Ein Hubela", "loc": "Gush Etzion", "tags": "einhubela spring 2021 03"},
{"f": "gush-etzion-album/image/einhubela2.jpg", "t": "Ein Hubela", "loc": "Gush Etzion", "tags": "einhubela spring 2021 05"},
{"f": "gush-etzion-album/image/einitzhak6.jpg", "t": "Ein Itzhak", "loc": "Gush Etzion", "tags": "einitzhak"},
{"f": "gush-etzion-album/image/einitzhak8.jpg", "t": "Ein Itzhak", "loc": "Gush Etzion", "tags": "einitzhak autumn 2019 10"},
{"f": "gush-etzion-album/image/einitzhak9.jpg", "t": "Ein Itzhak", "loc": "Gush Etzion", "tags": "einitzhak winter 2020 12"},
{"f": "gush-etzion-album/image/einlivne2.jpg", "t": "Ein Livne", "loc": "Gush Etzion", "tags": "einlivne autumn 2018 11"},
{"f": "gush-etzion-album/image/eintzurim2.jpg", "t": "Ein Tzurim", "loc": "Gush Etzion", "tags": "eintzurim spring 2017 04"},
{"f": "gush-etzion-album/image/eintzurim5.jpg", "t": "Ein Tzurim", "loc": "Gush Etzion", "tags": "eintzurim summer 2021 06"},
{"f": "gush-etzion-album/image/eintzurim6.jpg", "t": "Ein Tzurim", "loc": "Gush Etzion", "tags": "eintzurim summer 2021 06"},
{"f": "gush-etzion-album/image/eitam1.jpg", "t": "Eitam hill", "loc": "Gush Etzion", "tags": "eitam spring 2018 03"},
{"f": "gush-etzion-album/image/eitam5.jpg", "t": "Eitam hill", "loc": "Gush Etzion", "tags": "eitam spring 2018 03"},
{"f": "gush-etzion-album/image/emekbracha1.jpg", "t": "Bracha valley", "loc": "Gush Etzion", "tags": "emekbracha spring 2020 05"},
{"f": "gush-etzion-album/image/foresteretzayalim2.jpg", "t": "Eretz Ayalim forest", "loc": "Gush Etzion", "tags": "foresteretzayalim spring 2020 03"},
{"f": "gush-etzion-album/image/forestetzion1.jpg", "t": "Etzion forest", "loc": "Gush Etzion", "tags": "forestetzion winter 2020 02"},
{"f": "gush-etzion-album/image/forestetzion2.jpg", "t": "Etzion forest", "loc": "Gush Etzion", "tags": "forestetzion summer 2019 06"},
{"f": "gush-etzion-album/image/forestzait1.jpg", "t": "Zait forest, Efrat", "loc": "Gush Etzion", "tags": "forestzait autumn 2019 11"},
{"f": "gush-etzion-album/image/givathahish3.jpg", "t": "Hish hill, Alon Shvut", "loc": "Gush Etzion", "tags": "givathahish winter 2021 01"},
{"f": "gush-etzion-album/image/havatkashuela1.jpg", "t": "Kashuela farm", "loc": "Gush Etzion", "tags": "havatkashuela autumn 2019 09"},
{"f": "gush-etzion-album/image/havatsfarhamidbar1.jpg", "t": "Havat Sfar Hamidbar", "loc": "Gush Etzion", "tags": "havatsfarhamidbar winter 2019 02"},
{"f": "gush-etzion-album/image/havatsfarhamidbar3.jpg", "t": "Tulips in Havat Sfar Hamidbar", "loc": "Gush Etzion", "tags": "havatsfarhamidbar winter 2019 02"},
{"f": "gush-etzion-album/image/helmoniyot4.jpg", "t": "Sternbergia", "loc": "Gush Etzion", "tags": "helmoniyot autumn 2019 11"},
{"f": "gush-etzion-album/image/herodion3.jpg", "t": "Herodion", "loc": "Gush Etzion", "tags": "herodion spring 2013 04"},
{"f": "gush-etzion-album/image/herodion4.jpg", "t": "Herodion", "loc": "Gush Etzion", "tags": "herodion autumn 2020 11"},
{"f": "gush-etzion-album/image/hirbetjumjum6.jpg", "t": "Hirbet Jumjum", "loc": "Gush Etzion", "tags": "hirbetjumjum winter 2020 12"},
{"f": "gush-etzion-album/image/hurva1.jpg", "t": "Old ruins", "loc": "Gush Etzion", "tags": "hurva spring 2019 04"},
{"f": "gush-etzion-album/image/mishlatnekudahamishit1.jpg", "t": "Mishlat Nekuda Hamishit", "loc": "Gush Etzion", "tags": "mishlatnekudahamishit winter 2020 12"},
{"f": "gush-etzion-album/image/mishlatnekudahamishit2.jpg", "t": "Mishlat Nekuda Hamishit", "loc": "Gush Etzion", "tags": "mishlatnekudahamishit summer 2021 07"},
{"f": "gush-etzion-album/image/mishlatnekudahamishit3.jpg", "t": "Mishlat Nekuda Hamishit", "loc": "Gush Etzion", "tags": "mishlatnekudahamishit summer 2021 07"},
{"f": "gush-etzion-album/image/mitzporarifuld1.jpg", "t": "Ari Fuld's viewpoint", "loc": "Gush Etzion", "tags": "mitzporarifuld"},
{"f": "gush-etzion-album/image/mitzporarifuld2.jpg", "t": "Ari Fuld's viewpoint", "loc": "Gush Etzion", "tags": "mitzporarifuld spring 2019 04"},
{"f": "gush-etzion-album/image/mitzporderehavot1.jpg", "t": "Dereh Avot viewpoint", "loc": "Gush Etzion", "tags": "mitzporderehavot"},
{"f": "gush-etzion-album/image/mitzporderehavot2.jpg", "t": "Dereh Avot viewpoint", "loc": "Gush Etzion", "tags": "mitzporderehavot spring 2020 03"},
{"f": "gush-etzion-album/image/mitzporderehavot3.jpg", "t": "Dereh Avot viewpoint", "loc": "Gush Etzion", "tags": "mitzporderehavot"},
{"f": "gush-etzion-album/image/mitzporhaelef1.jpg", "t": "Haelef viewpoint", "loc": "Neve Daniel, Gush Etzion", "tags": "mitzporhaelef spring 2016 05"},
{"f": "gush-etzion-album/image/mitzporhaelef2.jpg", "t": "Haelef viewpoint", "loc": "Neve Daniel, Gush Etzion", "tags": "mitzporhaelef summer 2016 06"},
{"f": "gush-etzion-album/image/mitzporzvika1.jpg", "t": "Zvika viewpoint", "loc": "Gush Etzion", "tags": "mitzporzvika summer 2020 06"},
{"f": "gush-etzion-album/image/nahalamos1.jpg", "t": "Nahal Amos", "loc": "Gush Etzion", "tags": "nahalamos winter 2019 02"},
{"f": "gush-etzion-album/image/nahalamos2.jpg", "t": "Nahal Amos", "loc": "Gush Etzion", "tags": "nahalamos winter 2019 02"},
{"f": "gush-etzion-album/image/nahalhaetz1.jpg", "t": "Nahal Haetz", "loc": "Gush Etzion", "tags": "nahalhaetz winter 2021 01"},
{"f": "gush-etzion-album/image/nahalhaetz2.jpg", "t": "Nahal Haetz", "loc": "Gush Etzion", "tags": "nahalhaetz winter 2021 01"},
{"f": "gush-etzion-album/image/nahalhaetz3.jpg", "t": "Nahal Haetz", "loc": "Gush Etzion", "tags": "nahalhaetz winter 2021 01"},
{"f": "gush-etzion-album/image/nahalhaetz4.jpg", "t": "Nahal Haetz", "loc": "Gush Etzion", "tags": "nahalhaetz winter 2021 01"},
{"f": "gush-etzion-album/image/nahalhapirim7.jpg", "t": "Nahal Hapirim", "loc": "Gush Etzion", "tags": "nahalhapirim"},
{"f": "gush-etzion-album/image/nahalhapirim9.jpg", "t": "Nahal Hapirim", "loc": "Gush Etzion", "tags": "nahalhapirim spring 2018 04"},
{"f": "gush-etzion-album/image/nahalhapirim10.jpg", "t": "Nahal Hapirim", "loc": "Gush Etzion", "tags": "nahalhapirim autumn 2018 11"},
{"f": "gush-etzion-album/image/nahalhapirim13.jpg", "t": "Nahal Hapirim", "loc": "Gush Etzion", "tags": "nahalhapirim spring 2020 03"},
{"f": "gush-etzion-album/image/nahalhapirim14.jpg", "t": "Nahal Hapirim", "loc": "Gush Etzion", "tags": "nahalhapirim spring 2020 03"},
{"f": "gush-etzion-album/image/nahalhapirim15.jpg", "t": "Nahal Hapirim", "loc": "Gush Etzion", "tags": "nahalhapirim spring 2020 03"},
{"f": "gush-etzion-album/image/nahalhapirim16.jpg", "t": "Nahal Hapirim", "loc": "Gush Etzion", "tags": "nahalhapirim spring 2020 03"},
{"f": "gush-etzion-album/image/nahalhapirim18.jpg", "t": "Nahal Hapirim", "loc": "Gush Etzion", "tags": "nahalhapirim winter 2020 02"},
{"f": "gush-etzion-album/image/nahalhapirim19.jpg", "t": "Nahal Hapirim", "loc": "Gush Etzion", "tags": "nahalhapirim winter 2020 02"},
{"f": "gush-etzion-album/image/nahalhapirim23.jpg", "t": "Nahal Hapirim", "loc": "Gush Etzion", "tags": "nahalhapirim autumn 2019 11"},
{"f": "gush-etzion-album/image/nahalhapirim24.jpg", "t": "Nahal Hapirim", "loc": "Gush Etzion", "tags": "nahalhapirim"},
{"f": "gush-etzion-album/image/nahalhapirim25.jpg", "t": "Nahal Hapirim", "loc": "Gush Etzion", "tags": "nahalhapirim winter 2018 12"},
{"f": "gush-etzion-album/image/nahalhapirim26.jpg", "t": "Nahal Hapirim", "loc": "Gush Etzion", "tags": "nahalhapirim autumn 2020 11"},
{"f": "gush-etzion-album/image/nahalheletz1.jpg", "t": "Nahal Heletz", "loc": "Gush Etzion", "tags": "nahalheletz autumn 2019 09"},
{"f": "gush-etzion-album/image/nahalheletz5.jpg", "t": "Nahal Heletz", "loc": "Gush Etzion", "tags": "nahalheletz winter 2019 12"},
{"f": "gush-etzion-album/image/nahalheletz8.jpg", "t": "Nahal Heletz", "loc": "Gush Etzion", "tags": "nahalheletz summer 2021 06"},
{"f": "gush-etzion-album/image/nahalheletz9.jpg", "t": "Nahal Heletz", "loc": "Gush Etzion", "tags": "nahalheletz summer 2021 06"},
{"f": "gush-etzion-album/image/nahaltkoa2.jpg", "t": "Nahal Tkoa", "loc": "Gush Etzion", "tags": "nahaltkoa winter 2018 12"},
{"f": "gush-etzion-album/image/nahaltkoa3.jpg", "t": "Nahal Tkoa", "loc": "Gush Etzion", "tags": "nahaltkoa winter 2017 02"},
{"f": "gush-etzion-album/image/nahaltkoa4.jpg", "t": "Nahal Tkoa", "loc": "Gush Etzion", "tags": "nahaltkoa winter 2018 12"},
{"f": "gush-etzion-album/image/nahaltkoa5.jpg", "t": "Nahal Tkoa", "loc": "Gush Etzion", "tags": "nahaltkoa winter 2017 02"},
{"f": "gush-etzion-album/image/nahaltkoa6.jpg", "t": "Nahal Tkoa", "loc": "Gush Etzion", "tags": "nahaltkoa spring 2020 03"},
{"f": "gush-etzion-album/image/nahaltkoa9.jpg", "t": "Nahal Tkoa", "loc": "Gush Etzion", "tags": "nahaltkoa"},
{"f": "gush-etzion-album/image/nahaltkoa10.jpg", "t": "Nahal Tkoa", "loc": "Gush Etzion", "tags": "nahaltkoa winter 2020 02"},
{"f": "gush-etzion-album/image/nahaltkoa12.jpg", "t": "Nahal Tkoa", "loc": "Gush Etzion", "tags": "nahaltkoa spring 2021 03"},
{"f": "gush-etzion-album/image/nahaltkoa13.jpg", "t": "Nahal Tkoa", "loc": "Gush Etzion", "tags": "nahaltkoa winter 2021 01"},
{"f": "gush-etzion-album/image/nahaltkoa14.jpg", "t": "Nahal Tkoa", "loc": "Gush Etzion", "tags": "nahaltkoa winter 2020 12"},
{"f": "gush-etzion-album/image/nahaltkoa16.jpg", "t": "Nahal Tkoa", "loc": "Gush Etzion", "tags": "nahaltkoa winter 2019 12"},
{"f": "gush-etzion-album/image/nahaltkoa20.jpg", "t": "Nahal Tkoa", "loc": "Gush Etzion", "tags": "nahaltkoa winter 2021 01"},
{"f": "gush-etzion-album/image/nahaltzofit3.jpg", "t": "Nahal Tzofit", "loc": "Gush Etzion", "tags": "nahaltzofit spring 2019 04"},
{"f": "gush-etzion-album/image/nahaltzofit4.jpg", "t": "Nahal Tzofit", "loc": "Gush Etzion", "tags": "nahaltzofit spring 2020 05"},
{"f": "gush-etzion-album/image/nahaltzofit5.jpg", "t": "Nahal Tzofit", "loc": "Gush Etzion", "tags": "nahaltzofit winter 2020 12"},
{"f": "gush-etzion-album/image/nevedaniel1.jpg", "t": "Snow in Neve Daniel", "loc": "Gush Etzion", "tags": "nevedaniel winter 2013 12"},
{"f": "gush-etzion-album/image/nevedaniel2.jpg", "t": "Snow in Neve Daniel", "loc": "Gush Etzion", "tags": "nevedaniel winter 2013 01"},
{"f": "gush-etzion-album/image/nevedaniel3.jpg", "t": "Snow in Neve Daniel", "loc": "Gush Etzion", "tags": "nevedaniel winter 2013 12"},
{"f": "gush-etzion-album/image/nevedaniel4.jpg", "t": "Snow in Neve Daniel", "loc": "Gush Etzion", "tags": "nevedaniel winter 2013 01"},
{"f": "gush-etzion-album/image/nevedaniel7.jpg", "t": "Neve Daniel", "loc": "Gush Etzion", "tags": "nevedaniel autumn 2016 11"},
{"f": "gush-etzion-album/image/nevedaniel8.jpg", "t": "Neve Daniel", "loc": "Gush Etzion", "tags": "nevedaniel spring 2017 03"},
{"f": "gush-etzion-album/image/nevedaniel9.jpg", "t": "Snow in Neve Daniel", "loc": "Gush Etzion", "tags": "nevedaniel winter 2013 12"},
{"f": "gush-etzion-album/image/nevedaniel10.jpg", "t": "Snow in Neve Daniel", "loc": "Gush Etzion", "tags": "nevedaniel winter 2013 12"},
{"f": "gush-etzion-album/image/nevedaniel11.jpg", "t": "Neve Daniel", "loc": "Gush Etzion", "tags": "nevedaniel"},
{"f": "gush-etzion-album/image/nevedaniel12.jpg", "t": "Snow in Neve Daniel", "loc": "Gush Etzion", "tags": "nevedaniel winter 2013 12"},
{"f": "gush-etzion-album/image/nevedaniel13.jpg", "t": "Neve Daniel", "loc": "Gush Etzion", "tags": "nevedaniel spring 2016 03"},
{"f": "gush-etzion-album/image/nevedaniel14.jpg", "t": "Snow in Neve Daniel", "loc": "Gush Etzion", "tags": "nevedaniel winter 2015 02"},
{"f": "gush-etzion-album/image/nevedaniel15.jpg", "t": "Neve Daniel", "loc": "Gush Etzion", "tags": "nevedaniel spring 2017 03"},
{"f": "gush-etzion-album/image/ofanaim2.jpg", "t": "Gush Etzion single track", "loc": "Gush Etzion", "tags": "ofanaim autumn 2019 09"},
{"f": "gush-etzion-album/image/ofanaim4.jpg", "t": "Gush Etzion single track", "loc": "Gush Etzion", "tags": "ofanaim winter 2019 02"},
{"f": "gush-etzion-album/image/ofanaim5.jpg", "t": "Gush Etzion single track", "loc": "Gush Etzion", "tags": "ofanaim summer 2020 06"},
{"f": "gush-etzion-album/image/ofanaim6.jpg", "t": "Gush Etzion single track", "loc": "Gush Etzion", "tags": "ofanaim spring 2019 05"},
{"f": "gush-etzion-album/image/ofanaim7.jpg", "t": "Gush Etzion single track", "loc": "Gush Etzion", "tags": "ofanaim summer 2020 06"},
{"f": "gush-etzion-album/image/ozvegaon5.jpg", "t": "Oz VeGaon", "loc": "Gush Etzion", "tags": "ozvegaon spring 2017 04"},
{"f": "gush-etzion-album/image/rujmessabit1.jpg", "t": "Winter puddle", "loc": "Gush Etzion", "tags": "rujmessabit spring 2021 03"},
{"f": "gush-etzion-album/image/rujmessabit2.jpg", "t": "Winter puddle", "loc": "Gush Etzion", "tags": "rujmessabit spring 2021 03"},
{"f": "gush-etzion-album/image/sdeboaz3.jpg", "t": "Sde Boaz", "loc": "Gush Etzion", "tags": "sdeboaz spring 2021 03"},
{"f": "gush-etzion-album/image/tazpithabanim2.jpg", "t": "The Boys Promenade", "loc": "Gush Etzion", "tags": "tazpithabanim spring 2020 05"},
{"f": "gush-etzion-album/image/tazpithabanim3.jpg", "t": "The Boys Promenade", "loc": "Gush Etzion", "tags": "tazpithabanim autumn 2019 10"},
{"f": "gush-etzion-album/image/tazpithabanim4.jpg", "t": "The Boys Promenade", "loc": "Gush Etzion", "tags": "tazpithabanim spring 2019 05"},
{"f": "gush-etzion-album/image/yaartkoa3.jpg", "t": "Tkoa forest", "loc": "Gush Etzion", "tags": "yaartkoa winter 2020 02"},
{"f": "gush-etzion-album/image/yaartkoa4.jpg", "t": "Tkoa forest", "loc": "Gush Etzion", "tags": "yaartkoa winter 2020 02"},
{"f": "gush-etzion-album/image/yaartkoa6.jpg", "t": "Tkoa forest", "loc": "Gush Etzion", "tags": "yaartkoa winter 2020 02"},
{"f": "gush-etzion-album/image/yaartkoa9.jpg", "t": "Tkoa forest", "loc": "Gush Etzion", "tags": "yaartkoa winter 2021 01"}
]
}
